[
    {
        "name": "Wayne Ray"
    },
    {
        "name": "Bobby Spencer"
    },
    {
        "name": "Mattie Mendez"
    },
    {
        "name": "Ann Ryan"
    },
    {
        "name": "Clayton Harrington"
    },
    {
        "name": "Cordelia Pierce"
    },
    {
        "name": "Nathan Pope"
    },
    {
        "name": "Daniel Moran"
    },
    {
        "name": "Terry Benson"
    },
    {
        "name": "Louis Hines"
    },
    {
        "name": "Ronald Goodman"
    },
    {
        "name": "Jean Medina"
    },
    {
        "name": "Jared Clayton"
    },
    {
        "name": "Bess Allen"
    },
    {
        "name": "Pauline Fields"
    },
    {
        "name": "Harold McDonald"
    },
    {
        "name": "Josephine George"
    },
    {
        "name": "Randall Fernandez"
    },
    {
        "name": "Edgar Ingram"
    },
    {
        "name": "Herbert Rhodes"
    },
    {
        "name": "Barbara Arnold"
    },
    {
        "name": "Emma Santiago"
    },
    {
        "name": "Lou Hanson"
    },
    {
        "name": "Lou Lucas"
    },
    {
        "name": "Jeremy Massey"
    },
    {
        "name": "Charlotte Edwards"
    },
    {
        "name": "Inez Wells"
    },
    {
        "name": "Clayton Franklin"
    },
    {
        "name": "Eddie Clark"
    },
    {
        "name": "Marguerite Mason"
    },
    {
        "name": "Vernon Atkins"
    },
    {
        "name": "Connor Smith"
    },
    {
        "name": "Grace Hernandez"
    },
    {
        "name": "Mario Reese"
    },
    {
        "name": "Christopher Wilkerson"
    },
    {
        "name": "Julia Reed"
    },
    {
        "name": "Adelaide Martin"
    },
    {
        "name": "Leona Frank"
    },
    {
        "name": "Sylvia Simpson"
    },
    {
        "name": "Annie Greer"
    },
    {
        "name": "Lillie Quinn"
    },
    {
        "name": "Manuel Day"
    },
    {
        "name": "Polly Manning"
    },
    {
        "name": "Joel Reed"
    },
    {
        "name": "David Doyle"
    },
    {
        "name": "Roy Daniels"
    },
    {
        "name": "Jay Holmes"
    },
    {
        "name": "Evan Welch"
    },
    {
        "name": "Randall Cain"
    },
    {
        "name": "Allen Baker"
    },
    {
        "name": "Brent Brady"
    },
    {
        "name": "Adeline Evans"
    },
    {
        "name": "Elmer Briggs"
    },
    {
        "name": "Lina Holland"
    },
    {
        "name": "Ina Powell"
    },
    {
        "name": "Warren Clark"
    },
    {
        "name": "Travis Bryan"
    },
    {
        "name": "Mathilda Wagner"
    },
    {
        "name": "Chad Barnes"
    },
    {
        "name": "Ricky McCoy"
    },
    {
        "name": "Josie Schneider"
    },
    {
        "name": "Ralph Silva"
    },
    {
        "name": "Sara James"
    },
    {
        "name": "Alvin Barber"
    },
    {
        "name": "Hannah Valdez"
    },
    {
        "name": "Aaron Saunders"
    },
    {
        "name": "Vera Moore"
    },
    {
        "name": "Leah Riley"
    },
    {
        "name": "Madge Thomas"
    },
    {
        "name": "Ellen Smith"
    },
    {
        "name": "May Harvey"
    },
    {
        "name": "Lawrence Smith"
    },
    {
        "name": "Vernon Reyes"
    },
    {
        "name": "Vernon Morris"
    },
    {
        "name": "Emilie Gibson"
    },
    {
        "name": "Verna Floyd"
    },
    {
        "name": "Bertie Klein"
    },
    {
        "name": "Abbie Murphy"
    },
    {
        "name": "Vera Reynolds"
    },
    {
        "name": "Carolyn Francis"
    },
    {
        "name": "Jason Kelley"
    },
    {
        "name": "Walter Jackson"
    },
    {
        "name": "Carlos Burgess"
    },
    {
        "name": "Randy Griffith"
    }
]