[{
    "id": 1515,
    "run_location": 2,
    "vuserpercentexpectedsum": 100,
    "add_vusers_limit": 0,
    "name": "Ultima Sanity",
    "modified_date": "1520767667205",
    "create_by": "oded keret",
    "create_date": "6/22/2068",
    "start_time": "6/22/2068",
    "duration": "00:01:00",
    "description": null,
    "modified_by": "oded keret",
    "triggered_by": "oded keret",
    "running_job_id": 1392,
    "baseline_run": null,
    "last_run": 1392,
    "labels": ["test", "best"],
    "ui_status": "PASSED",
    "run_id": 1,
    "scheduledRuns": {
        "schedules": []
    }
}, {
    "id": 1514,
    "run_location": 2,
    "vuserpercentexpectedsum": 100,
    "add_vusers_limit": 0,
    "name": "Ultima Sanity",
    "modified_date": "1520427165627",
    "create_by": "Shlomi Nissim",
    "create_date": "9/4/2115",
    "start_time": "9/4/2115",
    "duration": "00:01:00",
    "description": null,
    "modified_by": "Shlomi Nissim",
    "triggered_by": "Shlomi Nissim",
    "running_job_id": 1391,
    "baseline_run": null,
    "last_run": 1391,
    "labels": ["test", "best"],
    "ui_status": "FAILED",
    "run_id": 2,
    "scheduledRuns": {
        "schedules": []
    }
}, {
    "id": 1513,
    "run_location": 2,
    "vuserpercentexpectedsum": 100,
    "add_vusers_limit": 0,
    "name": "Ultima Sanity",
    "modified_date": "1520402103738",
    "create_by": "oded keret",
    "create_date": "3/24/2108",
    "start_time": "3/24/2108",
    "duration": "00:01:00",
    "description": null,
    "modified_by": "oded keret",
    "triggered_by": "oded keret",
    "running_job_id": 1390,
    "baseline_run": null,
    "last_run": 1390,
    "labels": ["test", "best"],
    "ui_status": "PASSED",
    "run_id": 3,
    "scheduledRuns": {
        "schedules": []
    }
}, {
    "id": 1512,
    "run_location": 2,
    "vuserpercentexpectedsum": 100,
    "add_vusers_limit": 0,
    "name": "Ultima Sanity",
    "modified_date": "1520353683435",
    "create_by": "oded keret",
    "create_date": "6/15/2096",
    "start_time": "6/15/2096",
    "duration": "00:01:00",
    "description": null,
    "modified_by": "oded keret",
    "triggered_by": "oded keret",
    "running_job_id": 1388,
    "baseline_run": null,
    "last_run": 1388,
    "labels": ["test", "best"],
    "ui_status": "PASSED",
    "run_id": 4,
    "scheduledRuns": {
        "schedules": []
    }
}, {
    "id": 1511,
    "run_location": 2,
    "vuserpercentexpectedsum": 100,
    "add_vusers_limit": 0,
    "name": "Ultima Sanity",
    "modified_date": "1520410458574",
    "create_by": "oded keret",
    "create_date": "5/10/2101",
    "start_time": "5/10/2101",
    "duration": "00:01:00",
    "description": null,
    "modified_by": "oded keret",
    "triggered_by": "oded keret",
    "running_job_id": 1389,
    "baseline_run": null,
    "last_run": 1389,
    "labels": ["test", "best"],
    "ui_status": "PASSED",
    "run_id": 5,
    "scheduledRuns": {
        "schedules": []
    }
}, {
    "id": 1510,
    "run_location": 2,
    "vuserpercentexpectedsum": 100,
    "add_vusers_limit": 0,
    "name": "New Test 353",
    "modified_date": "1519801480474",
    "create_by": "Wei Sun",
    "create_date": "9/2/2048",
    "start_time": "9/2/2048",
    "duration": "00:01:00",
    "description": null,
    "modified_by": "Wei Sun",
    "triggered_by": "Wei Sun",
    "running_job_id": 1383,
    "baseline_run": null,
    "last_run": 1383,
    "labels": ["test", "best"],
    "ui_status": "FAILED",
    "run_id": 6,
    "scheduledRuns": {
        "schedules": []
    }
}, {
    "id": 1509,
    "run_location": 2,
    "vuserpercentexpectedsum": null,
    "add_vusers_limit": null,
    "name": "My Super Load Test",
    "modified_date": "1519788309888",
    "create_by": "Vicky Giavelli",
    "create_date": "8/9/2073",
    "start_time": "8/9/2073",
    "duration": "00:01:00",
    "description": null,
    "modified_by": "Vicky Giavelli",
    "triggered_by": "Vicky Giavelli",
    "running_job_id": null,
    "baseline_run": null,
    "last_run": null,
    "labels": ["test", "best"],
    "ui_status": "NEW",
    "run_id": 7,
    "scheduledRuns": {
        "schedules": []
    }
}, {
    "id": 1508,
    "run_location": 2,
    "vuserpercentexpectedsum": 100,
    "add_vusers_limit": 0,
    "name": "My Super Load Test",
    "modified_date": "1519119747068",
    "create_by": "oded keret",
    "create_date": "5/27/2033",
    "start_time": "5/27/2033",
    "duration": "00:01:00",
    "description": null,
    "modified_by": "oded keret",
    "triggered_by": "oded keret",
    "running_job_id": 1377,
    "baseline_run": null,
    "last_run": 1377,
    "labels": ["test", "best"],
    "ui_status": "FAILED",
    "run_id": 8,
    "scheduledRuns": {
        "schedules": []
    }
}, {
    "id": 1507,
    "run_location": 2,
    "vuserpercentexpectedsum": 100,
    "add_vusers_limit": 0,
    "name": "My Super Load Test",
    "modified_date": "1519635079201",
    "create_by": "oded keret",
    "create_date": "6/11/2068",
    "start_time": "6/11/2068",
    "duration": "00:01:00",
    "description": null,
    "modified_by": "Ayal Cohen",
    "triggered_by": "Ayal Cohen",
    "running_job_id": 1379,
    "baseline_run": null,
    "last_run": 1379,
    "labels": ["test", "best"],
    "ui_status": "SYSTEM_ERROR",
    "run_id": 9,
    "scheduledRuns": {
        "schedules": []
    }
}, {
    "id": 1506,
    "run_location": 2,
    "vuserpercentexpectedsum": 100,
    "add_vusers_limit": 0,
    "name": "My Super Load Test",
    "modified_date": "1518528795779",
    "create_by": "oded keret",
    "create_date": "11/10/2084",
    "start_time": "11/10/2084",
    "duration": "00:01:00",
    "description": null,
    "modified_by": "Yevgeniy Belov",
    "triggered_by": "Yevgeniy Belov",
    "running_job_id": 1381,
    "baseline_run": null,
    "last_run": 1381,
    "labels": ["test", "best"],
    "ui_status": "ABORTED",
    "run_id": 10,
    "scheduledRuns": {
        "schedules": []
    }
}, {
    "id": 1505,
    "run_location": 2,
    "vuserpercentexpectedsum": 100,
    "add_vusers_limit": 0,
    "name": "My Super Load Test",
    "modified_date": "1518348910609",
    "create_by": "oded keret",
    "create_date": "12/27/2047",
    "start_time": "12/27/2047",
    "duration": "00:01:00",
    "description": null,
    "modified_by": "oded keret",
    "triggered_by": "oded keret",
    "running_job_id": 1373,
    "baseline_run": null,
    "last_run": 1373,
    "labels": ["test", "best"],
    "ui_status": "PASSED",
    "run_id": 11,
    "scheduledRuns": {
        "schedules": []
    }
}, {
    "id": 1504,
    "run_location": 2,
    "vuserpercentexpectedsum": 100,
    "add_vusers_limit": 0,
    "name": "My Super Load Test",
    "modified_date": "1520224358738",
    "create_by": "Wei Sun",
    "create_date": "2/4/2096",
    "start_time": "2/4/2096",
    "duration": "00:01:00",
    "description": null,
    "modified_by": "Wei Sun",
    "triggered_by": "Wei Sun",
    "running_job_id": 1384,
    "baseline_run": null,
    "last_run": 1384,
    "labels": ["test", "best"],
    "ui_status": "PASSED",
    "run_id": 12,
    "scheduledRuns": {
        "schedules": []
    }
}, {
    "id": 1503,
    "run_location": 2,
    "vuserpercentexpectedsum": 100,
    "add_vusers_limit": 0,
    "name": "My Super Load Test",
    "modified_date": "1517385303541",
    "create_by": "oded keret",
    "create_date": "10/26/2102",
    "start_time": "10/26/2102",
    "duration": "00:01:00",
    "description": null,
    "modified_by": "oded keret",
    "triggered_by": "oded keret",
    "running_job_id": 1371,
    "baseline_run": null,
    "last_run": 1371,
    "labels": ["test", "best"],
    "ui_status": "FAILED",
    "run_id": 13,
    "scheduledRuns": {
        "schedules": []
    }
}, {
    "id": 1502,
    "run_location": 2,
    "vuserpercentexpectedsum": 100,
    "add_vusers_limit": 0,
    "name": "My Super Load Test",
    "modified_date": "1517381735113",
    "create_by": "oded keret",
    "create_date": "10/18/2107",
    "start_time": "10/18/2107",
    "duration": "00:01:00",
    "description": null,
    "modified_by": "oded keret",
    "triggered_by": "oded keret",
    "running_job_id": 1370,
    "baseline_run": null,
    "last_run": 1370,
    "labels": ["test", "best"],
    "ui_status": "FAILED",
    "run_id": 14,
    "scheduledRuns": {
        "schedules": []
    }
}, {
    "id": 1501,
    "run_location": 2,
    "vuserpercentexpectedsum": null,
    "add_vusers_limit": null,
    "name": "My Super Load Test",
    "modified_date": "1516891602506",
    "create_by": "Yevgeniy Belov",
    "create_date": "1/3/2107",
    "start_time": "1/3/2107",
    "duration": "00:01:00",
    "description": null,
    "modified_by": "Yevgeniy Belov",
    "triggered_by": "Yevgeniy Belov",
    "running_job_id": null,
    "baseline_run": null,
    "last_run": null,
    "labels": ["test", "best"],
    "ui_status": "NEW",
    "run_id": 15,
    "scheduledRuns": {
        "schedules": []
    }
}, {
    "id": 1500,
    "run_location": 2,
    "vuserpercentexpectedsum": 100,
    "add_vusers_limit": 0,
    "name": "My Super Load Test",
    "modified_date": "1515607525360",
    "create_by": "Yevgeniy Belov",
    "create_date": "3/1/2108",
    "start_time": "3/1/2108",
    "duration": "00:01:00",
    "description": null,
    "modified_by": "Liron Tzabari",
    "triggered_by": "Liron Tzabari",
    "running_job_id": 1369,
    "baseline_run": null,
    "last_run": 1369,
    "labels": ["test", "best"],
    "ui_status": "SYSTEM_ERROR",
    "run_id": 16,
    "scheduledRuns": {
        "schedules": []
    }
}, {
    "id": 1499,
    "run_location": 2,
    "vuserpercentexpectedsum": 100,
    "add_vusers_limit": 0,
    "name": "My Super Load Test",
    "modified_date": "1513060076845",
    "create_by": "oded keret",
    "create_date": "2/27/2105",
    "start_time": "2/27/2105",
    "duration": "00:01:00",
    "description": null,
    "modified_by": "oded keret",
    "triggered_by": "oded keret",
    "running_job_id": 1366,
    "baseline_run": null,
    "last_run": 1366,
    "labels": ["test", "best"],
    "ui_status": "PASSED",
    "run_id": 17,
    "scheduledRuns": {
        "schedules": []
    }
}, {
    "id": 1498,
    "run_location": 2,
    "vuserpercentexpectedsum": 100,
    "add_vusers_limit": 0,
    "name": "My Super Load Test",
    "modified_date": "1512973541507",
    "create_by": "oded keret",
    "create_date": "5/6/2092",
    "start_time": "5/6/2092",
    "duration": "00:01:00",
    "description": null,
    "modified_by": "oded keret",
    "triggered_by": "oded keret",
    "running_job_id": 1365,
    "baseline_run": null,
    "last_run": 1365,
    "labels": ["test", "best"],
    "ui_status": "PASSED",
    "run_id": 18,
    "scheduledRuns": {
        "schedules": []
    }
}, {
    "id": 1497,
    "run_location": 2,
    "vuserpercentexpectedsum": null,
    "add_vusers_limit": null,
    "name": "My Super Load Test",
    "modified_date": "1512647704554",
    "create_by": "Itzik Gan-Baruch",
    "create_date": "11/1/2088",
    "start_time": "11/1/2088",
    "duration": "00:01:00",
    "description": null,
    "modified_by": "Itzik Gan-Baruch",
    "triggered_by": "Itzik Gan-Baruch",
    "running_job_id": null,
    "baseline_run": null,
    "last_run": null,
    "labels": ["test", "best"],
    "ui_status": "NEW",
    "run_id": 19,
    "scheduledRuns": {
        "schedules": []
    }
}, {
    "id": 1496,
    "run_location": 2,
    "vuserpercentexpectedsum": null,
    "add_vusers_limit": null,
    "name": "My Super Load Test",
    "modified_date": "1512647207614",
    "create_by": "Itzik Gan-Baruch",
    "create_date": "3/27/2063",
    "start_time": "3/27/2063",
    "duration": "00:01:00",
    "description": null,
    "modified_by": "Itzik Gan-Baruch",
    "triggered_by": "Itzik Gan-Baruch",
    "running_job_id": null,
    "baseline_run": null,
    "last_run": null,
    "labels": ["test", "best"],
    "ui_status": "NEW",
    "run_id": 20,
    "scheduledRuns": {
        "schedules": []
    }
}, {
    "id": 1495,
    "run_location": 2,
    "vuserpercentexpectedsum": null,
    "add_vusers_limit": null,
    "name": "My Super Load Test",
    "modified_date": "1512576801288",
    "create_by": "oded keret",
    "create_date": "10/7/2112",
    "start_time": "10/7/2112",
    "duration": "00:01:00",
    "description": null,
    "modified_by": "oded keret",
    "triggered_by": "oded keret",
    "running_job_id": null,
    "baseline_run": null,
    "last_run": null,
    "labels": ["test", "best"],
    "ui_status": "NEW",
    "run_id": 21,
    "scheduledRuns": {
        "schedules": []
    }
}, {
    "id": 1494,
    "run_location": 2,
    "vuserpercentexpectedsum": 100,
    "add_vusers_limit": 0,
    "name": "My Super Load Test",
    "modified_date": "1518615126092",
    "create_by": "Yevgeniy Belov",
    "create_date": "7/29/2054",
    "start_time": "7/29/2054",
    "duration": "00:01:00",
    "description": null,
    "modified_by": "Yevgeniy Belov",
    "triggered_by": "Yevgeniy Belov",
    "running_job_id": null,
    "baseline_run": null,
    "last_run": null,
    "labels": ["test", "best"],
    "ui_status": "NEW",
    "run_id": 22,
    "scheduledRuns": {
        "schedules": []
    }
}, {
    "id": 1493,
    "run_location": 2,
    "vuserpercentexpectedsum": 100,
    "add_vusers_limit": 0,
    "name": "My Super Load Test",
    "modified_date": "1509617549178",
    "create_by": "Itzik Gan-Baruch",
    "create_date": "2/12/2100",
    "start_time": "2/12/2100",
    "duration": "00:01:00",
    "description": null,
    "modified_by": "Itzik Gan-Baruch",
    "triggered_by": "Itzik Gan-Baruch",
    "running_job_id": 1363,
    "baseline_run": null,
    "last_run": 1363,
    "labels": ["test", "best"],
    "ui_status": "FAILED",
    "run_id": 23,
    "scheduledRuns": {
        "schedules": []
    }
}, {
    "id": 1488,
    "run_location": 2,
    "vuserpercentexpectedsum": 100,
    "add_vusers_limit": 0,
    "name": "My Super Load Test",
    "modified_date": "1509261400508",
    "create_by": "Ayal Cohen",
    "create_date": "2/25/2107",
    "start_time": "2/25/2107",
    "duration": "00:01:00",
    "description": null,
    "modified_by": "Ayal Cohen",
    "triggered_by": "Ayal Cohen",
    "running_job_id": 1359,
    "baseline_run": null,
    "last_run": 1359,
    "labels": ["test", "best"],
    "ui_status": "PASSED",
    "run_id": 24,
    "scheduledRuns": {
        "schedules": []
    }
}, {
    "id": 1487,
    "run_location": 2,
    "vuserpercentexpectedsum": 100,
    "add_vusers_limit": 0,
    "name": "My Super Load Test",
    "modified_date": "1507128658164",
    "create_by": "Gaspare Marino",
    "create_date": "10/12/2119",
    "start_time": "10/12/2119",
    "duration": "00:01:00",
    "description": null,
    "modified_by": "Gaspare Marino",
    "triggered_by": "Gaspare Marino",
    "running_job_id": 1356,
    "baseline_run": null,
    "last_run": 1356,
    "labels": ["test", "best"],
    "ui_status": "FAILED",
    "run_id": 25,
    "scheduledRuns": {
        "schedules": []
    }
}, {
    "id": 1486,
    "run_location": 2,
    "vuserpercentexpectedsum": 100,
    "add_vusers_limit": 0,
    "name": "My Super Load Test",
    "modified_date": "1509536331731",
    "create_by": "oded keret",
    "create_date": "4/12/2028",
    "start_time": "4/12/2028",
    "duration": "00:01:00",
    "description": null,
    "modified_by": "Ray Tomany",
    "triggered_by": "Ray Tomany",
    "running_job_id": 1358,
    "baseline_run": 1358,
    "last_run": 1358,
    "labels": ["test", "best"],
    "ui_status": "FAILED",
    "run_id": 26,
    "scheduledRuns": {
        "schedules": []
    }
}, {
    "id": 1485,
    "run_location": 2,
    "vuserpercentexpectedsum": 100,
    "add_vusers_limit": 0,
    "name": "My Super Load Test",
    "modified_date": "1507050828544",
    "create_by": "oded keret",
    "create_date": "12/3/2069",
    "start_time": "12/3/2069",
    "duration": "00:01:00",
    "description": null,
    "modified_by": "oded keret",
    "triggered_by": "oded keret",
    "running_job_id": 1354,
    "baseline_run": null,
    "last_run": 1354,
    "labels": ["test", "best"],
    "ui_status": "FAILED",
    "run_id": 27,
    "scheduledRuns": {
        "schedules": []
    }
}, {
    "id": 1484,
    "run_location": 2,
    "vuserpercentexpectedsum": null,
    "add_vusers_limit": null,
    "name": "My Super Load Test",
    "modified_date": "1504517554780",
    "create_by": "Amit Hasson",
    "create_date": "2/4/2083",
    "start_time": "2/4/2083",
    "duration": "00:01:00",
    "description": null,
    "modified_by": "Amit Hasson",
    "triggered_by": "Amit Hasson",
    "running_job_id": null,
    "baseline_run": null,
    "last_run": null,
    "labels": ["test", "best"],
    "ui_status": "NEW",
    "run_id": 28,
    "scheduledRuns": {
        "schedules": []
    }
}, {
    "id": 1483,
    "run_location": 2,
    "vuserpercentexpectedsum": 100,
    "add_vusers_limit": 0,
    "name": "My Super Load Test",
    "modified_date": "1505053318023",
    "create_by": "Ayal Cohen",
    "create_date": "9/27/2069",
    "start_time": "9/27/2069",
    "duration": "00:01:00",
    "description": null,
    "modified_by": "Aviran Harom",
    "triggered_by": "Aviran Harom",
    "running_job_id": null,
    "baseline_run": null,
    "last_run": null,
    "labels": ["test", "best"],
    "ui_status": "NEW",
    "run_id": 29,
    "scheduledRuns": {
        "schedules": []
    }
}, {
    "id": 1482,
    "run_location": 2,
    "vuserpercentexpectedsum": 100,
    "add_vusers_limit": 0,
    "name": "My Super Load Test",
    "modified_date": "1504123471135",
    "create_by": "Shane Evans",
    "create_date": "9/12/2041",
    "start_time": "9/12/2041",
    "duration": "00:01:00",
    "description": null,
    "modified_by": "Shane Evans",
    "triggered_by": "Shane Evans",
    "running_job_id": 1352,
    "baseline_run": null,
    "last_run": 1352,
    "labels": ["test", "best"],
    "ui_status": "FAILED",
    "run_id": 30,
    "scheduledRuns": {
        "schedules": []
    }
}, {
    "id": 1480,
    "run_location": 2,
    "vuserpercentexpectedsum": null,
    "add_vusers_limit": null,
    "name": "My Super Load Test",
    "modified_date": "1502387392600",
    "create_by": "Vicky Villalobos",
    "create_date": "12/12/2079",
    "start_time": "12/12/2079",
    "duration": "00:01:00",
    "description": null,
    "modified_by": "Vicky Villalobos",
    "triggered_by": "Vicky Villalobos",
    "running_job_id": null,
    "baseline_run": null,
    "last_run": null,
    "labels": ["test", "best"],
    "ui_status": "NEW",
    "run_id": 31,
    "scheduledRuns": {
        "schedules": []
    }
}, {
    "id": 1479,
    "run_location": 2,
    "vuserpercentexpectedsum": 100,
    "add_vusers_limit": 0,
    "name": "My Super Load Test",
    "modified_date": "1502169473768",
    "create_by": "oded keret",
    "create_date": "5/31/2043",
    "start_time": "5/31/2043",
    "duration": "00:01:00",
    "description": null,
    "modified_by": "oded keret",
    "triggered_by": "oded keret",
    "running_job_id": null,
    "baseline_run": null,
    "last_run": null,
    "labels": ["test", "best"],
    "ui_status": "NEW",
    "run_id": 32,
    "scheduledRuns": {
        "schedules": []
    }
}, {
    "id": 1478,
    "run_location": 2,
    "vuserpercentexpectedsum": 100,
    "add_vusers_limit": 100,
    "name": "My Super Load Test",
    "modified_date": "1502211205555",
    "create_by": "oded keret",
    "create_date": "12/3/2110",
    "start_time": "12/3/2110",
    "duration": "00:01:00",
    "description": null,
    "modified_by": "oded keret",
    "triggered_by": "oded keret",
    "running_job_id": 1351,
    "baseline_run": null,
    "last_run": 1351,
    "labels": ["test", "best"],
    "ui_status": "FAILED",
    "run_id": 33,
    "scheduledRuns": {
        "schedules": []
    }
}, {
    "id": 1477,
    "run_location": 2,
    "vuserpercentexpectedsum": null,
    "add_vusers_limit": null,
    "name": "My Super Load Test",
    "modified_date": "1505644329038",
    "create_by": "Aviad blumenfeld",
    "create_date": "5/13/2068",
    "start_time": "5/13/2068",
    "duration": "00:01:00",
    "description": null,
    "modified_by": "David Peer",
    "triggered_by": "David Peer",
    "running_job_id": null,
    "baseline_run": null,
    "last_run": null,
    "labels": ["test", "best"],
    "ui_status": "NEW",
    "run_id": 34,
    "scheduledRuns": {
        "schedules": []
    }
}, {
    "id": 1476,
    "run_location": 2,
    "vuserpercentexpectedsum": 100,
    "add_vusers_limit": 0,
    "name": "My Super Load Test",
    "modified_date": "1501517406952",
    "create_by": "oded keret",
    "create_date": "4/13/2045",
    "start_time": "4/13/2045",
    "duration": "00:01:00",
    "description": null,
    "modified_by": "oded keret",
    "triggered_by": "oded keret",
    "running_job_id": 1343,
    "baseline_run": null,
    "last_run": 1343,
    "labels": ["test", "best"],
    "ui_status": "FAILED",
    "run_id": 35,
    "scheduledRuns": {
        "schedules": []
    }
}, {
    "id": 1475,
    "run_location": 2,
    "vuserpercentexpectedsum": 100,
    "add_vusers_limit": 0,
    "name": "My Super Load Test",
    "modified_date": "1500798652736",
    "create_by": "oded keret",
    "create_date": "4/28/2063",
    "start_time": "4/28/2063",
    "duration": "00:01:00",
    "description": null,
    "modified_by": "oded keret",
    "triggered_by": "oded keret",
    "running_job_id": 1342,
    "baseline_run": null,
    "last_run": 1342,
    "labels": ["test", "best"],
    "ui_status": "PASSED",
    "run_id": 36,
    "scheduledRuns": {
        "schedules": []
    }
}, {
    "id": 1474,
    "run_location": 2,
    "vuserpercentexpectedsum": 100,
    "add_vusers_limit": 0,
    "name": "My Super Load Test",
    "modified_date": "1500395368968",
    "create_by": "Gaspare Marino",
    "create_date": "11/5/2067",
    "start_time": "11/5/2067",
    "duration": "00:01:00",
    "description": null,
    "modified_by": "Gaspare Marino",
    "triggered_by": "Gaspare Marino",
    "running_job_id": null,
    "baseline_run": null,
    "last_run": null,
    "labels": ["test", "best"],
    "ui_status": "NEW",
    "run_id": 37,
    "scheduledRuns": {
        "schedules": []
    }
}, {
    "id": 1473,
    "run_location": 2,
    "vuserpercentexpectedsum": null,
    "add_vusers_limit": null,
    "name": "My Super Load Test",
    "modified_date": "1500201234866",
    "create_by": "Yevgeniy Belov",
    "create_date": "12/11/2050",
    "start_time": "12/11/2050",
    "duration": "00:01:00",
    "description": null,
    "modified_by": "Yevgeniy Belov",
    "triggered_by": "Yevgeniy Belov",
    "running_job_id": null,
    "baseline_run": null,
    "last_run": null,
    "labels": ["test", "best"],
    "ui_status": "NEW",
    "run_id": 38,
    "scheduledRuns": {
        "schedules": []
    }
}, {
    "id": 1472,
    "run_location": 2,
    "vuserpercentexpectedsum": null,
    "add_vusers_limit": null,
    "name": "My Super Load Test",
    "modified_date": "1499931957073",
    "create_by": "Amit Hasson",
    "create_date": "11/28/2078",
    "start_time": "11/28/2078",
    "duration": "00:01:00",
    "description": null,
    "modified_by": "Amit Hasson",
    "triggered_by": "Amit Hasson",
    "running_job_id": null,
    "baseline_run": null,
    "last_run": null,
    "labels": ["test", "best"],
    "ui_status": "NEW",
    "run_id": 39,
    "scheduledRuns": {
        "schedules": []
    }
}, {
    "id": 1471,
    "run_location": 2,
    "vuserpercentexpectedsum": null,
    "add_vusers_limit": null,
    "name": "My Super Load Test",
    "modified_date": "1499930980418",
    "create_by": "Amit Hasson",
    "create_date": "8/8/2062",
    "start_time": "8/8/2062",
    "duration": "00:01:00",
    "description": null,
    "modified_by": "Shlomi Nissim",
    "triggered_by": "Shlomi Nissim",
    "running_job_id": null,
    "baseline_run": null,
    "last_run": null,
    "labels": ["test", "best"],
    "ui_status": "NEW",
    "run_id": 40,
    "scheduledRuns": {
        "schedules": []
    }
}, {
    "id": 1470,
    "run_location": 2,
    "vuserpercentexpectedsum": 100,
    "add_vusers_limit": 0,
    "name": "My Super Load Test",
    "modified_date": "1499850674007",
    "create_by": "Gaspare Marino",
    "create_date": "5/21/2063",
    "start_time": "5/21/2063",
    "duration": "00:01:00",
    "description": null,
    "modified_by": "Gaspare Marino",
    "triggered_by": "Gaspare Marino",
    "running_job_id": 1341,
    "baseline_run": null,
    "last_run": 1341,
    "labels": ["test", "best"],
    "ui_status": "FAILED",
    "run_id": 41,
    "scheduledRuns": {
        "schedules": []
    }
}, {
    "id": 1469,
    "run_location": 2,
    "vuserpercentexpectedsum": 100,
    "add_vusers_limit": 0,
    "name": "My Super Load Test",
    "modified_date": "1499775090223",
    "create_by": "oded keret",
    "create_date": "9/30/2031",
    "start_time": "9/30/2031",
    "duration": "00:01:00",
    "description": null,
    "modified_by": "oded keret",
    "triggered_by": "oded keret",
    "running_job_id": 1340,
    "baseline_run": null,
    "last_run": 1340,
    "labels": ["test", "best"],
    "ui_status": "PASSED",
    "run_id": 42,
    "scheduledRuns": {
        "schedules": []
    }
}, {
    "id": 1468,
    "run_location": 2,
    "vuserpercentexpectedsum": 100,
    "add_vusers_limit": 0,
    "name": "My Super Load Test",
    "modified_date": "1499762807341",
    "create_by": "oded keret",
    "create_date": "2/17/2103",
    "start_time": "2/17/2103",
    "duration": "00:01:00",
    "description": null,
    "modified_by": "oded keret",
    "triggered_by": "oded keret",
    "running_job_id": 1339,
    "baseline_run": null,
    "last_run": 1339,
    "labels": ["test", "best"],
    "ui_status": "FAILED",
    "run_id": 43,
    "scheduledRuns": {
        "schedules": []
    }
}, {
    "id": 1467,
    "run_location": 2,
    "vuserpercentexpectedsum": 100,
    "add_vusers_limit": 0,
    "name": "My Super Load Test",
    "modified_date": "1499761205033",
    "create_by": "oded keret",
    "create_date": "4/1/2059",
    "start_time": "4/1/2059",
    "duration": "00:01:00",
    "description": null,
    "modified_by": "oded keret",
    "triggered_by": "oded keret",
    "running_job_id": 1338,
    "baseline_run": null,
    "last_run": 1338,
    "labels": ["test", "best"],
    "ui_status": "FAILED",
    "run_id": 44,
    "scheduledRuns": {
        "schedules": []
    }
}, {
    "id": 1466,
    "run_location": 2,
    "vuserpercentexpectedsum": 100,
    "add_vusers_limit": 0,
    "name": "My Super Load Test",
    "modified_date": "1499751394712",
    "create_by": "oded keret",
    "create_date": "4/27/2101",
    "start_time": "4/27/2101",
    "duration": "00:01:00",
    "description": null,
    "modified_by": "oded keret",
    "triggered_by": "oded keret",
    "running_job_id": 1336,
    "baseline_run": null,
    "last_run": 1336,
    "labels": ["test", "best"],
    "ui_status": "PASSED",
    "run_id": 45,
    "scheduledRuns": {
        "schedules": []
    }
}, {
    "id": 1465,
    "run_location": 2,
    "vuserpercentexpectedsum": null,
    "add_vusers_limit": null,
    "name": "My Super Load Test",
    "modified_date": "1499607318372",
    "create_by": "Gaspare Marino",
    "create_date": "3/2/2023",
    "start_time": "3/2/2023",
    "duration": "00:01:00",
    "description": null,
    "modified_by": "oded keret",
    "triggered_by": "oded keret",
    "running_job_id": null,
    "baseline_run": null,
    "last_run": null,
    "labels": ["test", "best"],
    "ui_status": "NEW",
    "run_id": 46,
    "scheduledRuns": {
        "schedules": []
    }
}, {
    "id": 1432,
    "run_location": 2,
    "vuserpercentexpectedsum": 100,
    "add_vusers_limit": 0,
    "name": "My Super Load Test",
    "modified_date": "1498138216168",
    "create_by": "Ayal Cohen",
    "create_date": "3/12/2116",
    "start_time": "3/12/2116",
    "duration": "00:01:00",
    "description": null,
    "modified_by": "Ayal Cohen",
    "triggered_by": "Ayal Cohen",
    "running_job_id": 1298,
    "baseline_run": null,
    "last_run": 1298,
    "labels": ["test", "best"],
    "ui_status": "ABORTED",
    "run_id": 47,
    "scheduledRuns": {
        "schedules": []
    }
}, {
    "id": 1431,
    "run_location": 2,
    "vuserpercentexpectedsum": 100,
    "add_vusers_limit": 0,
    "name": "My Super Load Test",
    "modified_date": "1499762970563",
    "create_by": "David Peer",
    "create_date": "9/18/2062",
    "start_time": "9/18/2062",
    "duration": "00:01:00",
    "description": null,
    "modified_by": "David Peer",
    "triggered_by": "David Peer",
    "running_job_id": 1332,
    "baseline_run": null,
    "last_run": 1332,
    "labels": ["test", "best"],
    "ui_status": "PASSED",
    "run_id": 48,
    "scheduledRuns": {
        "schedules": []
    }
}, {
    "id": 1430,
    "run_location": 2,
    "vuserpercentexpectedsum": null,
    "add_vusers_limit": null,
    "name": "My Super Load Test",
    "modified_date": "1497967665428",
    "create_by": "Avi Arjuan",
    "create_date": "12/14/2033",
    "start_time": "12/14/2033",
    "duration": "00:01:00",
    "description": null,
    "modified_by": "Avi Arjuan",
    "triggered_by": "Avi Arjuan",
    "running_job_id": null,
    "baseline_run": null,
    "last_run": null,
    "labels": ["test", "best"],
    "ui_status": "NEW",
    "run_id": 49,
    "scheduledRuns": {
        "schedules": []
    }
}, {
    "id": 1429,
    "run_location": 2,
    "vuserpercentexpectedsum": 100,
    "add_vusers_limit": 0,
    "name": "My Super Load Test",
    "modified_date": "1497955903631",
    "create_by": "oded keret",
    "create_date": "9/3/2095",
    "start_time": "9/3/2095",
    "duration": "00:01:00",
    "description": null,
    "modified_by": "oded keret",
    "triggered_by": "oded keret",
    "running_job_id": 1295,
    "baseline_run": null,
    "last_run": 1295,
    "labels": ["test", "best"],
    "ui_status": "PASSED",
    "run_id": 50,
    "scheduledRuns": {
        "schedules": []
    }
}, {
    "id": 1428,
    "run_location": 2,
    "vuserpercentexpectedsum": 100,
    "add_vusers_limit": 0,
    "name": "My Super Load Test",
    "modified_date": "1497877917673",
    "create_by": "oded keret",
    "create_date": "1/16/2028",
    "start_time": "1/16/2028",
    "duration": "00:01:00",
    "description": null,
    "modified_by": "oded keret",
    "triggered_by": "oded keret",
    "running_job_id": 1294,
    "baseline_run": null,
    "last_run": 1294,
    "labels": ["test", "best"],
    "ui_status": "PASSED",
    "run_id": 51,
    "scheduledRuns": {
        "schedules": []
    }
}, {
    "id": 1427,
    "run_location": 2,
    "vuserpercentexpectedsum": 100,
    "add_vusers_limit": 0,
    "name": "My Super Load Test",
    "modified_date": "1497629757109",
    "create_by": "Ayal Cohen",
    "create_date": "12/22/2030",
    "start_time": "12/22/2030",
    "duration": "00:01:00",
    "description": null,
    "modified_by": "Ayal Cohen",
    "triggered_by": "Ayal Cohen",
    "running_job_id": 1292,
    "baseline_run": null,
    "last_run": 1292,
    "labels": ["test", "best"],
    "ui_status": "PASSED",
    "run_id": 52,
    "scheduledRuns": {
        "schedules": []
    }
}, {
    "id": 1426,
    "run_location": 2,
    "vuserpercentexpectedsum": 100,
    "add_vusers_limit": 0,
    "name": "My Super Load Test",
    "modified_date": "1497530870941",
    "create_by": "oded keret",
    "create_date": "11/21/2078",
    "start_time": "11/21/2078",
    "duration": "00:01:00",
    "description": null,
    "modified_by": "oded keret",
    "triggered_by": "oded keret",
    "running_job_id": 1293,
    "baseline_run": null,
    "last_run": 1293,
    "labels": ["test", "best"],
    "ui_status": "PASSED",
    "run_id": 53,
    "scheduledRuns": {
        "schedules": []
    }
}, {
    "id": 1393,
    "run_location": 2,
    "vuserpercentexpectedsum": 100,
    "add_vusers_limit": 0,
    "name": "My Super Load Test",
    "modified_date": "1497375699931",
    "create_by": "oded keret",
    "create_date": "5/4/2078",
    "start_time": "5/4/2078",
    "duration": "00:01:00",
    "description": null,
    "modified_by": "oded keret",
    "triggered_by": "oded keret",
    "running_job_id": 1258,
    "baseline_run": null,
    "last_run": 1258,
    "labels": ["test", "best"],
    "ui_status": "PASSED",
    "run_id": 54,
    "scheduledRuns": {
        "schedules": []
    }
}, {
    "id": 1392,
    "run_location": 2,
    "vuserpercentexpectedsum": 100,
    "add_vusers_limit": 0,
    "name": "My Super Load Test",
    "modified_date": "1497369168680",
    "create_by": "oded keret",
    "create_date": "9/14/2104",
    "start_time": "9/14/2104",
    "duration": "00:01:00",
    "description": null,
    "modified_by": "oded keret",
    "triggered_by": "oded keret",
    "running_job_id": 1257,
    "baseline_run": null,
    "last_run": 1257,
    "labels": ["test", "best"],
    "ui_status": "PASSED",
    "run_id": 55,
    "scheduledRuns": {
        "schedules": []
    }
}, {
    "id": 1391,
    "run_location": 2,
    "vuserpercentexpectedsum": 100,
    "add_vusers_limit": 0,
    "name": "My Super Load Test",
    "modified_date": "1497343374381",
    "create_by": "Avi Arjuan",
    "create_date": "10/23/2079",
    "start_time": "10/23/2079",
    "duration": "00:01:00",
    "description": null,
    "modified_by": "Avi Arjuan",
    "triggered_by": "Avi Arjuan",
    "running_job_id": null,
    "baseline_run": null,
    "last_run": null,
    "labels": ["test", "best"],
    "ui_status": "NEW",
    "run_id": 56,
    "scheduledRuns": {
        "schedules": []
    }
}, {
    "id": 1390,
    "run_location": 2,
    "vuserpercentexpectedsum": 100,
    "add_vusers_limit": 0,
    "name": "My Super Load Test",
    "modified_date": "1496953966176",
    "create_by": "Itzik Gan-Baruch",
    "create_date": "7/30/2062",
    "start_time": "7/30/2062",
    "duration": "00:01:00",
    "description": null,
    "modified_by": "Itzik Gan-Baruch",
    "triggered_by": "Itzik Gan-Baruch",
    "running_job_id": null,
    "baseline_run": null,
    "last_run": null,
    "labels": ["test", "best"],
    "ui_status": "NEW",
    "run_id": 57,
    "scheduledRuns": {
        "schedules": []
    }
}, {
    "id": 1389,
    "run_location": 2,
    "vuserpercentexpectedsum": null,
    "add_vusers_limit": null,
    "name": "My Super Load Test",
    "modified_date": "1496953462694",
    "create_by": "Itzik Gan-Baruch",
    "create_date": "6/13/2028",
    "start_time": "6/13/2028",
    "duration": "00:01:00",
    "description": null,
    "modified_by": "Itzik Gan-Baruch",
    "triggered_by": "Itzik Gan-Baruch",
    "running_job_id": null,
    "baseline_run": null,
    "last_run": null,
    "labels": ["test", "best"],
    "ui_status": "NEW",
    "run_id": 58,
    "scheduledRuns": {
        "schedules": []
    }
}, {
    "id": 1388,
    "run_location": 2,
    "vuserpercentexpectedsum": 100,
    "add_vusers_limit": 0,
    "name": "My Super Load Test",
    "modified_date": "1496872128528",
    "create_by": "Shane Evans",
    "create_date": "1/26/2022",
    "start_time": "1/26/2022",
    "duration": "00:01:00",
    "description": null,
    "modified_by": "Shane Evans",
    "triggered_by": "Shane Evans",
    "running_job_id": 1253,
    "baseline_run": null,
    "last_run": 1253,
    "labels": ["test", "best"],
    "ui_status": "ABORTED",
    "run_id": 59,
    "scheduledRuns": {
        "schedules": []
    }
}, {
    "id": 1387,
    "run_location": 2,
    "vuserpercentexpectedsum": 100,
    "add_vusers_limit": 0,
    "name": "My Super Load Test",
    "modified_date": "1496825307056",
    "create_by": "Amit Hasson",
    "create_date": "8/18/2106",
    "start_time": "8/18/2106",
    "duration": "00:01:00",
    "description": null,
    "modified_by": "Amit Hasson",
    "triggered_by": "Amit Hasson",
    "running_job_id": 1252,
    "baseline_run": null,
    "last_run": 1252,
    "labels": ["test", "best"],
    "ui_status": "PASSED",
    "run_id": 60,
    "scheduledRuns": {
        "schedules": []
    }
}, {
    "id": 1386,
    "run_location": 2,
    "vuserpercentexpectedsum": 100,
    "add_vusers_limit": 0,
    "name": "My Super Load Test",
    "modified_date": "1496824011032",
    "create_by": "Amit Hasson",
    "create_date": "2/13/2062",
    "start_time": "2/13/2062",
    "duration": "00:01:00",
    "description": null,
    "modified_by": "Amit Hasson",
    "triggered_by": "Amit Hasson",
    "running_job_id": 1251,
    "baseline_run": null,
    "last_run": 1251,
    "labels": ["test", "best"],
    "ui_status": "PASSED",
    "run_id": 61,
    "scheduledRuns": {
        "schedules": []
    }
}, {
    "id": 1385,
    "run_location": 2,
    "vuserpercentexpectedsum": null,
    "add_vusers_limit": null,
    "name": "My Super Load Test",
    "modified_date": "1496795663122",
    "create_by": "Shane Evans",
    "create_date": "1/18/2051",
    "start_time": "1/18/2051",
    "duration": "00:01:00",
    "description": null,
    "modified_by": "Shane Evans",
    "triggered_by": "Shane Evans",
    "running_job_id": null,
    "baseline_run": null,
    "last_run": null,
    "labels": ["test", "best"],
    "ui_status": "NEW",
    "run_id": 62,
    "scheduledRuns": {
        "schedules": []
    }
}, {
    "id": 1384,
    "run_location": 2,
    "vuserpercentexpectedsum": 100,
    "add_vusers_limit": 0,
    "name": "My Super Load Test",
    "modified_date": "1496784983194",
    "create_by": "Itzik Gan-Baruch",
    "create_date": "8/7/2078",
    "start_time": "8/7/2078",
    "duration": "00:01:00",
    "description": null,
    "modified_by": "Itzik Gan-Baruch",
    "triggered_by": "Itzik Gan-Baruch",
    "running_job_id": 1250,
    "baseline_run": null,
    "last_run": 1250,
    "labels": ["test", "best"],
    "ui_status": "FAILED",
    "run_id": 63,
    "scheduledRuns": {
        "schedules": []
    }
}, {
    "id": 1383,
    "run_location": 2,
    "vuserpercentexpectedsum": 100,
    "add_vusers_limit": 0,
    "name": "My Super Load Test",
    "modified_date": "1496747262537",
    "create_by": "oded keret",
    "create_date": "2/11/2079",
    "start_time": "2/11/2079",
    "duration": "00:01:00",
    "description": null,
    "modified_by": "oded keret",
    "triggered_by": "oded keret",
    "running_job_id": 1249,
    "baseline_run": null,
    "last_run": 1249,
    "labels": ["test", "best"],
    "ui_status": "HALTED",
    "run_id": 64,
    "scheduledRuns": {
        "schedules": []
    }
}, {
    "id": 1382,
    "run_location": 2,
    "vuserpercentexpectedsum": 100,
    "add_vusers_limit": 0,
    "name": "My Super Load Test",
    "modified_date": "1496739236387",
    "create_by": "oded keret",
    "create_date": "7/31/2032",
    "start_time": "7/31/2032",
    "duration": "00:01:00",
    "description": null,
    "modified_by": "oded keret",
    "triggered_by": "oded keret",
    "running_job_id": null,
    "baseline_run": null,
    "last_run": null,
    "labels": ["test", "best"],
    "ui_status": "NEW",
    "run_id": 65,
    "scheduledRuns": {
        "schedules": []
    }
}, {
    "id": 1381,
    "run_location": 2,
    "vuserpercentexpectedsum": null,
    "add_vusers_limit": null,
    "name": "My Super Load Test",
    "modified_date": "1496705549231",
    "create_by": "Itzik Gan-Baruch",
    "create_date": "8/14/2026",
    "start_time": "8/14/2026",
    "duration": "00:01:00",
    "description": null,
    "modified_by": "Itzik Gan-Baruch",
    "triggered_by": "Itzik Gan-Baruch",
    "running_job_id": 1247,
    "baseline_run": null,
    "last_run": 1247,
    "labels": ["test", "best"],
    "ui_status": "FAILED",
    "run_id": 66,
    "scheduledRuns": {
        "schedules": []
    }
}, {
    "id": 1379,
    "run_location": 2,
    "vuserpercentexpectedsum": 100,
    "add_vusers_limit": 0,
    "name": "Discover",
    "modified_date": "1496705330771",
    "create_by": "Itzik Gan-Baruch",
    "create_date": "1/29/2114",
    "start_time": "1/29/2114",
    "duration": "00:01:00",
    "description": null,
    "modified_by": "Itzik Gan-Baruch",
    "triggered_by": "Itzik Gan-Baruch",
    "running_job_id": null,
    "baseline_run": null,
    "last_run": null,
    "labels": ["test", "best"],
    "ui_status": "NEW",
    "run_id": 67,
    "scheduledRuns": {
        "schedules": []
    }
}, {
    "id": 1378,
    "run_location": 2,
    "vuserpercentexpectedsum": 100,
    "add_vusers_limit": 0,
    "name": "Nike Demo",
    "modified_date": "1497341579806",
    "create_by": "oded keret",
    "create_date": "11/17/2087",
    "start_time": "11/17/2087",
    "duration": "00:01:00",
    "description": null,
    "modified_by": "Avi Arjuan",
    "triggered_by": "Avi Arjuan",
    "running_job_id": 1256,
    "baseline_run": null,
    "last_run": 1256,
    "labels": ["test", "best"],
    "ui_status": "PASSED",
    "run_id": 68,
    "scheduledRuns": {
        "schedules": []
    }
}, {
    "id": 1377,
    "run_location": 2,
    "vuserpercentexpectedsum": 100,
    "add_vusers_limit": 0,
    "name": "Nike Demo",
    "modified_date": "1496731023465",
    "create_by": "oded keret",
    "create_date": "5/20/2090",
    "start_time": "5/20/2090",
    "duration": "00:01:00",
    "description": null,
    "modified_by": "oded keret",
    "triggered_by": "oded keret",
    "running_job_id": 1248,
    "baseline_run": null,
    "last_run": 1248,
    "labels": ["test", "best"],
    "ui_status": "HALTED",
    "run_id": 69,
    "scheduledRuns": {
        "schedules": []
    }
}, {
    "id": 1376,
    "run_location": 2,
    "vuserpercentexpectedsum": 100,
    "add_vusers_limit": 0,
    "name": "Nike Demo",
    "modified_date": "1496659291664",
    "create_by": "oded keret",
    "create_date": "1/31/2113",
    "start_time": "1/31/2113",
    "duration": "00:01:00",
    "description": null,
    "modified_by": "oded keret",
    "triggered_by": "oded keret",
    "running_job_id": 1244,
    "baseline_run": null,
    "last_run": 1244,
    "labels": ["test", "best"],
    "ui_status": "FAILED",
    "run_id": 70,
    "scheduledRuns": {
        "schedules": []
    }
}, {
    "id": 1375,
    "run_location": 2,
    "vuserpercentexpectedsum": null,
    "add_vusers_limit": null,
    "name": "Nike Demo",
    "modified_date": "1496609121424",
    "create_by": "Avi Arjuan",
    "create_date": "10/17/2030",
    "start_time": "10/17/2030",
    "duration": "00:01:00",
    "description": null,
    "modified_by": "Avi Arjuan",
    "triggered_by": "Avi Arjuan",
    "running_job_id": null,
    "baseline_run": null,
    "last_run": null,
    "labels": ["test", "best"],
    "ui_status": "NEW",
    "run_id": 71,
    "scheduledRuns": {
        "schedules": []
    }
}, {
    "id": 1374,
    "run_location": 2,
    "vuserpercentexpectedsum": 100,
    "add_vusers_limit": 0,
    "name": "Nike Demo",
    "modified_date": "1496564119883",
    "create_by": "Ron Toledo",
    "create_date": "11/26/2050",
    "start_time": "11/26/2050",
    "duration": "00:01:00",
    "description": null,
    "modified_by": "Ron Toledo",
    "triggered_by": "Ron Toledo",
    "running_job_id": 1243,
    "baseline_run": null,
    "last_run": 1243,
    "labels": ["test", "best"],
    "ui_status": "FAILED",
    "run_id": 72,
    "scheduledRuns": {
        "schedules": []
    }
}, {
    "id": 1341,
    "run_location": 0,
    "vuserpercentexpectedsum": null,
    "add_vusers_limit": 0,
    "name": "Nike Demo",
    "modified_date": "1496747671654",
    "create_by": "oded keret",
    "create_date": "7/27/2047",
    "start_time": "7/27/2047",
    "duration": "00:01:00",
    "description": null,
    "modified_by": "oded keret",
    "triggered_by": "oded keret",
    "running_job_id": 1210,
    "baseline_run": null,
    "last_run": 1210,
    "labels": ["test", "best"],
    "ui_status": "FAILED",
    "run_id": 73,
    "scheduledRuns": {
        "schedules": []
    }
}, {
    "id": 1340,
    "run_location": 0,
    "vuserpercentexpectedsum": null,
    "add_vusers_limit": 0,
    "name": "Nike Demo",
    "modified_date": "1495527539458",
    "create_by": "omer felder",
    "create_date": "4/22/2021",
    "start_time": "4/22/2021",
    "duration": "00:01:00",
    "description": null,
    "modified_by": "omer felder",
    "triggered_by": "omer felder",
    "running_job_id": 1209,
    "baseline_run": null,
    "last_run": 1209,
    "labels": ["test", "best"],
    "ui_status": "PASSED",
    "run_id": 74,
    "scheduledRuns": {
        "schedules": []
    }
}, {
    "id": 1339,
    "run_location": 0,
    "vuserpercentexpectedsum": null,
    "add_vusers_limit": null,
    "name": "Nike Demo",
    "modified_date": "1495203725157",
    "create_by": "Kristina Avrionova",
    "create_date": "3/29/2075",
    "start_time": "3/29/2075",
    "duration": "00:01:00",
    "description": null,
    "modified_by": "Kristina Avrionova",
    "triggered_by": "Kristina Avrionova",
    "running_job_id": 1207,
    "baseline_run": null,
    "last_run": 1207,
    "labels": ["test", "best"],
    "ui_status": "FAILED",
    "run_id": 75,
    "scheduledRuns": {
        "schedules": []
    }
}, {
    "id": 1338,
    "run_location": 0,
    "vuserpercentexpectedsum": null,
    "add_vusers_limit": 0,
    "name": "Agile live at Dublin",
    "modified_date": "1495113073621",
    "create_by": "oded keret",
    "create_date": "9/29/2117",
    "start_time": "9/29/2117",
    "duration": "00:01:00",
    "description": null,
    "modified_by": "oded keret",
    "triggered_by": "oded keret",
    "running_job_id": 1208,
    "baseline_run": null,
    "last_run": 1208,
    "labels": ["test", "best"],
    "ui_status": "ABORTED",
    "run_id": 76,
    "scheduledRuns": {
        "schedules": []
    }
}, {
    "id": 1337,
    "run_location": 0,
    "vuserpercentexpectedsum": null,
    "add_vusers_limit": 0,
    "name": "Agile Live",
    "modified_date": "1495112663476",
    "create_by": "oded keret",
    "create_date": "2/24/2077",
    "start_time": "2/24/2077",
    "duration": "00:01:00",
    "description": null,
    "modified_by": "oded keret",
    "triggered_by": "oded keret",
    "running_job_id": null,
    "baseline_run": null,
    "last_run": null,
    "labels": ["test", "best"],
    "ui_status": "NEW",
    "run_id": 77,
    "scheduledRuns": {
        "schedules": []
    }
}, {
    "id": 1336,
    "run_location": 0,
    "vuserpercentexpectedsum": null,
    "add_vusers_limit": 0,
    "name": "DemoIntesa",
    "modified_date": "1495102076466",
    "create_by": "Gaspare Marino",
    "create_date": "4/10/2063",
    "start_time": "4/10/2063",
    "duration": "00:01:00",
    "description": null,
    "modified_by": "Gaspare Marino",
    "triggered_by": "Gaspare Marino",
    "running_job_id": 1205,
    "baseline_run": null,
    "last_run": 1205,
    "labels": ["test", "best"],
    "ui_status": "PASSED",
    "run_id": 78,
    "scheduledRuns": {
        "schedules": []
    }
}, {
    "id": 1335,
    "run_location": 0,
    "vuserpercentexpectedsum": null,
    "add_vusers_limit": 0,
    "name": "DemoGas",
    "modified_date": "1495100001443",
    "create_by": "Gaspare Marino",
    "create_date": "9/19/2087",
    "start_time": "9/19/2087",
    "duration": "00:01:00",
    "description": null,
    "modified_by": "Gaspare Marino",
    "triggered_by": "Gaspare Marino",
    "running_job_id": 1204,
    "baseline_run": null,
    "last_run": 1204,
    "labels": ["test", "best"],
    "ui_status": "PASSED",
    "run_id": 79,
    "scheduledRuns": {
        "schedules": []
    }
}, {
    "id": 1334,
    "run_location": 0,
    "vuserpercentexpectedsum": null,
    "add_vusers_limit": 0,
    "name": "DemoDublin5",
    "modified_date": "1495097269384",
    "create_by": "Gaspare Marino",
    "create_date": "4/23/2051",
    "start_time": "4/23/2051",
    "duration": "00:01:00",
    "description": null,
    "modified_by": "Gaspare Marino",
    "triggered_by": "Gaspare Marino",
    "running_job_id": 1203,
    "baseline_run": null,
    "last_run": 1203,
    "labels": ["test", "best"],
    "ui_status": "PASSED",
    "run_id": 80,
    "scheduledRuns": {
        "schedules": []
    }
}, {
    "id": 1333,
    "run_location": 0,
    "vuserpercentexpectedsum": null,
    "add_vusers_limit": null,
    "name": "New Test 331",
    "modified_date": "1495017195736",
    "create_by": "Itzik Gan-Baruch",
    "create_date": "3/5/2041",
    "start_time": "3/5/2041",
    "duration": "00:01:00",
    "description": null,
    "modified_by": "Itzik Gan-Baruch",
    "triggered_by": "Itzik Gan-Baruch",
    "running_job_id": 1202,
    "baseline_run": null,
    "last_run": 1202,
    "labels": ["test", "best"],
    "ui_status": "FAILED",
    "run_id": 81,
    "scheduledRuns": {
        "schedules": []
    }
}, {
    "id": 1332,
    "run_location": 0,
    "vuserpercentexpectedsum": null,
    "add_vusers_limit": null,
    "name": "New Test 330",
    "modified_date": "1495017118567",
    "create_by": "Itzik Gan-Baruch",
    "create_date": "10/18/2071",
    "start_time": "10/18/2071",
    "duration": "00:01:00",
    "description": null,
    "modified_by": "Itzik Gan-Baruch",
    "triggered_by": "Itzik Gan-Baruch",
    "running_job_id": null,
    "baseline_run": null,
    "last_run": null,
    "labels": ["test", "best"],
    "ui_status": "NEW",
    "run_id": 82,
    "scheduledRuns": {
        "schedules": []
    }
}, {
    "id": 1331,
    "run_location": 0,
    "vuserpercentexpectedsum": null,
    "add_vusers_limit": null,
    "name": "New Test 329",
    "modified_date": "1495014767180",
    "create_by": "Itzik Gan-Baruch",
    "create_date": "11/13/2039",
    "start_time": "11/13/2039",
    "duration": "00:01:00",
    "description": null,
    "modified_by": "Itzik Gan-Baruch",
    "triggered_by": "Itzik Gan-Baruch",
    "running_job_id": null,
    "baseline_run": null,
    "last_run": null,
    "labels": ["test", "best"],
    "ui_status": "NEW",
    "run_id": 83,
    "scheduledRuns": {
        "schedules": []
    }
}, {
    "id": 1330,
    "run_location": 1,
    "vuserpercentexpectedsum": null,
    "add_vusers_limit": 0,
    "name": "New Test 328",
    "modified_date": "1494988339120",
    "create_by": "Wei Sun",
    "create_date": "5/20/2035",
    "start_time": "5/20/2035",
    "duration": "00:01:00",
    "description": null,
    "modified_by": "Wei Sun",
    "triggered_by": "Wei Sun",
    "running_job_id": null,
    "baseline_run": null,
    "last_run": null,
    "labels": ["test", "best"],
    "ui_status": "NEW",
    "run_id": 84,
    "scheduledRuns": {
        "schedules": []
    }
}, {
    "id": 1329,
    "run_location": 0,
    "vuserpercentexpectedsum": null,
    "add_vusers_limit": null,
    "name": "New Test 327",
    "modified_date": "1494988016306",
    "create_by": "Wei Sun",
    "create_date": "5/16/2051",
    "start_time": "5/16/2051",
    "duration": "00:01:00",
    "description": null,
    "modified_by": "Wei Sun",
    "triggered_by": "Wei Sun",
    "running_job_id": null,
    "baseline_run": null,
    "last_run": null,
    "labels": ["test", "best"],
    "ui_status": "NEW",
    "run_id": 85,
    "scheduledRuns": {
        "schedules": []
    }
}, {
    "id": 1328,
    "run_location": 0,
    "vuserpercentexpectedsum": null,
    "add_vusers_limit": 0,
    "name": "Live at Dublin",
    "modified_date": "1494943607167",
    "create_by": "oded keret",
    "create_date": "7/21/2110",
    "start_time": "7/21/2110",
    "duration": "00:01:00",
    "description": null,
    "modified_by": "oded keret",
    "triggered_by": "oded keret",
    "running_job_id": 1201,
    "baseline_run": null,
    "last_run": 1201,
    "labels": ["test", "best"],
    "ui_status": "FAILED",
    "run_id": 86,
    "scheduledRuns": {
        "schedules": []
    }
}, {
    "id": 1327,
    "run_location": 0,
    "vuserpercentexpectedsum": null,
    "add_vusers_limit": null,
    "name": "New Test 326",
    "modified_date": "1494855305382",
    "create_by": "Avi Arjuan",
    "create_date": "11/14/2027",
    "start_time": "11/14/2027",
    "duration": "00:01:00",
    "description": null,
    "modified_by": "Avi Arjuan",
    "triggered_by": "Avi Arjuan",
    "running_job_id": null,
    "baseline_run": null,
    "last_run": null,
    "labels": ["test", "best"],
    "ui_status": "NEW",
    "run_id": 87,
    "scheduledRuns": {
        "schedules": []
    }
}, {
    "id": 1326,
    "run_location": 0,
    "vuserpercentexpectedsum": null,
    "add_vusers_limit": null,
    "name": "New Test 325",
    "modified_date": "1494837942104",
    "create_by": "Avi Arjuan",
    "create_date": "6/10/2090",
    "start_time": "6/10/2090",
    "duration": "00:01:00",
    "description": null,
    "modified_by": "Avi Arjuan",
    "triggered_by": "Avi Arjuan",
    "running_job_id": null,
    "baseline_run": null,
    "last_run": null,
    "labels": ["test", "best"],
    "ui_status": "NEW",
    "run_id": 88,
    "scheduledRuns": {
        "schedules": []
    }
}, {
    "id": 1325,
    "run_location": 0,
    "vuserpercentexpectedsum": null,
    "add_vusers_limit": null,
    "name": "New Test 324",
    "modified_date": "1494837131555",
    "create_by": "Avi Arjuan",
    "create_date": "10/7/2096",
    "start_time": "10/7/2096",
    "duration": "00:01:00",
    "description": null,
    "modified_by": "Avi Arjuan",
    "triggered_by": "Avi Arjuan",
    "running_job_id": null,
    "baseline_run": null,
    "last_run": null,
    "labels": ["test", "best"],
    "ui_status": "NEW",
    "run_id": 89,
    "scheduledRuns": {
        "schedules": []
    }
}, {
    "id": 1324,
    "run_location": 0,
    "vuserpercentexpectedsum": null,
    "add_vusers_limit": null,
    "name": "New Test 323",
    "modified_date": "1494584052728",
    "create_by": "Ray Tomany",
    "create_date": "3/16/2087",
    "start_time": "3/16/2087",
    "duration": "00:01:00",
    "description": null,
    "modified_by": "Ray Tomany",
    "triggered_by": "Ray Tomany",
    "running_job_id": null,
    "baseline_run": null,
    "last_run": null,
    "labels": ["test", "best"],
    "ui_status": "NEW",
    "run_id": 90,
    "scheduledRuns": {
        "schedules": []
    }
}, {
    "id": 1323,
    "run_location": 0,
    "vuserpercentexpectedsum": null,
    "add_vusers_limit": 0,
    "name": "New Test 322",
    "modified_date": "1494424662496",
    "create_by": "Firas Matar",
    "create_date": "10/20/2056",
    "start_time": "10/20/2056",
    "duration": "00:01:00",
    "description": null,
    "modified_by": "Firas Matar",
    "triggered_by": "Firas Matar",
    "running_job_id": null,
    "baseline_run": null,
    "last_run": null,
    "labels": ["test", "best"],
    "ui_status": "NEW",
    "run_id": 91,
    "scheduledRuns": {
        "schedules": []
    }
}, {
    "id": 1322,
    "run_location": 0,
    "vuserpercentexpectedsum": null,
    "add_vusers_limit": null,
    "name": "New Test 321",
    "modified_date": "1494417438090",
    "create_by": "Firas Matar",
    "create_date": "5/20/2079",
    "start_time": "5/20/2079",
    "duration": "00:01:00",
    "description": null,
    "modified_by": "Firas Matar",
    "triggered_by": "Firas Matar",
    "running_job_id": 1200,
    "baseline_run": null,
    "last_run": 1200,
    "labels": ["test", "best"],
    "ui_status": "HALTED",
    "run_id": 92,
    "scheduledRuns": {
        "schedules": []
    }
}, {
    "id": 1321,
    "run_location": 0,
    "vuserpercentexpectedsum": null,
    "add_vusers_limit": 0,
    "name": "New Test 320",
    "modified_date": "1494328226642",
    "create_by": "Firas Matar",
    "create_date": "6/25/2101",
    "start_time": "6/25/2101",
    "duration": "00:01:00",
    "description": null,
    "modified_by": "oded keret",
    "triggered_by": "oded keret",
    "running_job_id": null,
    "baseline_run": null,
    "last_run": null,
    "labels": ["test", "best"],
    "ui_status": "NEW",
    "run_id": 93,
    "scheduledRuns": {
        "schedules": []
    }
}, {
    "id": 1320,
    "run_location": 0,
    "vuserpercentexpectedsum": null,
    "add_vusers_limit": 0,
    "name": "New Test 319",
    "modified_date": "1494315756179",
    "create_by": "Avi Arjuan",
    "create_date": "2/27/2108",
    "start_time": "2/27/2108",
    "duration": "00:01:00",
    "description": null,
    "modified_by": "Avi Arjuan",
    "triggered_by": "Avi Arjuan",
    "running_job_id": null,
    "baseline_run": null,
    "last_run": null,
    "labels": ["test", "best"],
    "ui_status": "NEW",
    "run_id": 94,
    "scheduledRuns": {
        "schedules": []
    }
}, {
    "id": 1319,
    "run_location": 0,
    "vuserpercentexpectedsum": null,
    "add_vusers_limit": 0,
    "name": "New Test 318",
    "modified_date": "1494242168119",
    "create_by": "Avi Arjuan",
    "create_date": "8/12/2101",
    "start_time": "8/12/2101",
    "duration": "00:01:00",
    "description": null,
    "modified_by": "Firas Matar",
    "triggered_by": "Firas Matar",
    "running_job_id": null,
    "baseline_run": null,
    "last_run": null,
    "labels": ["test", "best"],
    "ui_status": "NEW",
    "run_id": 95,
    "scheduledRuns": {
        "schedules": []
    }
}, {
    "id": 1318,
    "run_location": 0,
    "vuserpercentexpectedsum": null,
    "add_vusers_limit": null,
    "name": "New Test 317",
    "modified_date": "1493215561915",
    "create_by": "Avi Arjuan",
    "create_date": "3/8/2084",
    "start_time": "3/8/2084",
    "duration": "00:01:00",
    "description": null,
    "modified_by": "Avi Arjuan",
    "triggered_by": "Avi Arjuan",
    "running_job_id": null,
    "baseline_run": null,
    "last_run": null,
    "labels": ["test", "best"],
    "ui_status": "NEW",
    "run_id": 96,
    "scheduledRuns": {
        "schedules": []
    }
}, {
    "id": 1317,
    "run_location": 0,
    "vuserpercentexpectedsum": null,
    "add_vusers_limit": 0,
    "name": "New Test 316",
    "modified_date": "1493117830648",
    "create_by": "Firas Matar",
    "create_date": "5/18/2102",
    "start_time": "5/18/2102",
    "duration": "00:01:00",
    "description": null,
    "modified_by": "David Peer",
    "triggered_by": "David Peer",
    "running_job_id": null,
    "baseline_run": null,
    "last_run": null,
    "labels": ["test", "best"],
    "ui_status": "NEW",
    "run_id": 97,
    "scheduledRuns": {
        "schedules": []
    }
}, {
    "id": 1316,
    "run_location": 0,
    "vuserpercentexpectedsum": null,
    "add_vusers_limit": null,
    "name": "New Test 315",
    "modified_date": "1491391287233",
    "create_by": "Firas Matar",
    "create_date": "4/11/2019",
    "start_time": "4/11/2019",
    "duration": "00:01:00",
    "description": null,
    "modified_by": "Firas Matar",
    "triggered_by": "Firas Matar",
    "running_job_id": null,
    "baseline_run": null,
    "last_run": null,
    "labels": ["test", "best"],
    "ui_status": "NEW",
    "run_id": 98,
    "scheduledRuns": {
        "schedules": []
    }
}, {
    "id": 1315,
    "run_location": 0,
    "vuserpercentexpectedsum": null,
    "add_vusers_limit": null,
    "name": "New Test 314",
    "modified_date": "1491309386010",
    "create_by": "Gaspare Marino",
    "create_date": "11/19/2072",
    "start_time": "11/19/2072",
    "duration": "00:01:00",
    "description": null,
    "modified_by": "Firas Matar",
    "triggered_by": "Firas Matar",
    "running_job_id": null,
    "baseline_run": null,
    "last_run": null,
    "labels": ["test", "best"],
    "ui_status": "NEW",
    "run_id": 99,
    "scheduledRuns": {
        "schedules": []
    }
}, {
    "id": 1314,
    "run_location": 0,
    "vuserpercentexpectedsum": null,
    "add_vusers_limit": null,
    "name": "New Test 313",
    "modified_date": "1491306585146",
    "create_by": "Firas Matar",
    "create_date": "5/26/2089",
    "start_time": "5/26/2089",
    "duration": "00:01:00",
    "description": null,
    "modified_by": "Firas Matar",
    "triggered_by": "Firas Matar",
    "running_job_id": null,
    "baseline_run": null,
    "last_run": null,
    "labels": ["test", "best"],
    "ui_status": "NEW",
    "run_id": 100,
    "scheduledRuns": {
        "schedules": []
    }
}]
